yazit/__init__.py
yazit/unyazit.py
yazit/yazit.py
yaz_it-0.3.0.dist-info/METADATA
yaz_it-0.3.0.dist-info/WHEEL
yaz_it-0.3.0.dist-info/entry_points.txt
yaz_it-0.3.0.dist-info/top_level.txt
yaz_it-0.3.0.dist-info/RECORD
